django_ckeditor_5/__init__.py
django_ckeditor_5/fields.py
django_ckeditor_5/forms.py
django_ckeditor_5/storage.py
django_ckeditor_5/urls.py
django_ckeditor_5/views.py
django_ckeditor_5/widgets.py
django_ckeditor_5/static/django_ckeditor_5/app.js
django_ckeditor_5/static/django_ckeditor_5/exemple.js
django_ckeditor_5/static/django_ckeditor_5/dist/bundle.js
django_ckeditor_5/static/django_ckeditor_5/dist/bundle.js.map
django_ckeditor_5/static/django_ckeditor_5/dist/index.html
django_ckeditor_5/static/django_ckeditor_5/dist/styles.css
django_ckeditor_5/static/django_ckeditor_5/dist/styles.css.map
django_ckeditor_5/static/django_ckeditor_5/src/ckeditor.js
django_ckeditor_5/static/django_ckeditor_5/src/override-django.css
django_ckeditor_5/static/django_ckeditor_5/src/custom_plugins/imageediting.js
django_ckeditor_5/static/django_ckeditor_5/src/custom_plugins/imagetitle.js
django_ckeditor_5/static/django_ckeditor_5/src/custom_plugins/imagewithtitle.js
django_ckeditor_5/static/django_ckeditor_5/src/custom_plugins/imagetitle/imagetitlecommand.js
django_ckeditor_5/static/django_ckeditor_5/src/custom_plugins/imagetitle/imagetitleediting.js
django_ckeditor_5/static/django_ckeditor_5/src/custom_plugins/imagetitle/imagetitleui.js
django_ckeditor_5/static/django_ckeditor_5/src/custom_plugins/imagetitle/ui/titleformview.js
django_ckeditor_5/static/django_ckeditor_5/src/custom_plugins/sign/sign.css
django_ckeditor_5/static/django_ckeditor_5/src/custom_plugins/sign/sign.js
django_ckeditor_5/static/django_ckeditor_5/src/custom_plugins/sign/signcommand.js
django_ckeditor_5/static/django_ckeditor_5/src/custom_plugins/sign/signediting.js
django_ckeditor_5/static/django_ckeditor_5/src/custom_plugins/sign/signui.js
django_ckeditor_5/static/django_ckeditor_5/src/custom_plugins/theme/title.svg
django_ckeditor_5/static/django_ckeditor_5/src/custom_plugins/theme/titleform.css
django_ckeditor_5/templates/django_ckeditor_5/widget.html
ckeditor5_trendig-0.6.2.dist-info/LICENSE.txt
ckeditor5_trendig-0.6.2.dist-info/METADATA
ckeditor5_trendig-0.6.2.dist-info/WHEEL
ckeditor5_trendig-0.6.2.dist-info/top_level.txt
ckeditor5_trendig-0.6.2.dist-info/RECORD
