Metadata-Version: 2.1
Name: ckeditor5-trendig
Version: 0.6.2
Summary: CKEditor 5 for django labtrendig to s3.
Home-page: https://github.com/bjvta/django_ckeditor_5/
Author: Brandon
Author-email: bjvtamayo78@gmail.com
License: BSD 2-clause
Classifier: Programming Language :: Python :: 3.5
License-File: LICENSE.txt
